factories/__init__.py
rest_email_manager/__init__.py
rest_email_manager/admin.py
rest_email_manager/apps.py
rest_email_manager/models.py
rest_email_manager/serializers.py
rest_email_manager/settings.py
rest_email_manager/urls.py
rest_email_manager/utils.py
rest_email_manager/views.py
rest_email_manager/migrations/0001_initial.py
rest_email_manager/migrations/__init__.py
rest_email_manager/templates/rest_email_manager/emails/email_update_notification.txt
rest_email_manager/templates/rest_email_manager/emails/verify_email.txt
tests/__init__.py
tests/conftest.py
tests/settings.py
tests/test_apps.py
tests/test_views.py
tests/urls.py
django_rest_email_manager-1.0.2.dist-info/LICENSE
django_rest_email_manager-1.0.2.dist-info/METADATA
django_rest_email_manager-1.0.2.dist-info/WHEEL
django_rest_email_manager-1.0.2.dist-info/top_level.txt
django_rest_email_manager-1.0.2.dist-info/RECORD
